tweedie/__init__.py
tweedie/_version.py
tweedie/tweedie_dist.py
tweedie-0.0.9.dist-info/LICENSE.txt
tweedie-0.0.9.dist-info/METADATA
tweedie-0.0.9.dist-info/WHEEL
tweedie-0.0.9.dist-info/top_level.txt
tweedie-0.0.9.dist-info/RECORD
