Metadata-Version: 2.1
Name: tweedie
Version: 0.0.9
Summary: Tweedie distribution estimations of pdf and cdf
Home-page: https://github.com/thequackdaddy/tweedie
Author: Peter Quackenbush
Author-email: pquack@gmail.com
License: BSD
Keywords: statsmodels scipy distribution tweedie
Platform: UNKNOWN
Requires-Dist: scipy
Requires-Dist: numpy
Provides-Extra: dev
Requires-Dist: pytest ; extra == 'dev'
Requires-Dist: tox ; extra == 'dev'
